phydrus/__init__.py
phydrus/decorators.py
phydrus/model.py
phydrus/plot.py
phydrus/profile.py
phydrus/read.py
phydrus/utils.py
phydrus/version.py
phydrus-0.2.0.dist-info/LICENSE
phydrus-0.2.0.dist-info/METADATA
phydrus-0.2.0.dist-info/WHEEL
phydrus-0.2.0.dist-info/top_level.txt
phydrus-0.2.0.dist-info/RECORD
