Metadata-Version: 2.1
Name: phydrus
Version: 0.2.0
Summary: Python implementation of the HYDRUS-1D model
Home-page: https://github.com/phydrus/phydrus
Author: Raoul Collenteur, Matevz Vremec, Giuseppe Brunetti
Author-email: raoul.collenteur@uni-graz.at
License: GNU General public version 3.0
Project-URL: Source, https://github.com/phydrus/phydrus
Project-URL: Tracker, https://github.com/phydrus/phydrus/issues
Project-URL: Help, https://github.com/phydrus/phydrus/discussions
Platform: Windows
Platform: Mac OS-X
Classifier: Development Status :: 4 - Beta
Classifier: Intended Audience :: Science/Research
Classifier: Intended Audience :: Other Audience
Classifier: License :: OSI Approved :: GNU Lesser General Public License v3 (LGPLv3)
Classifier: Programming Language :: Python :: 3.7
Classifier: Programming Language :: Python :: 3.8
Classifier: Programming Language :: Python :: 3.9
Classifier: Topic :: Scientific/Engineering :: Hydrology
Requires-Dist: numpy (>=1.15)
Requires-Dist: matplotlib (>=2.0)
Requires-Dist: pandas (>=1.0)
Requires-Dist: scipy (>=1.1)
